{"seq":9,"ts":1777244106,"frames":[{"id":"c71ea3680382fba4db292f49e","seq":3,"status":"closing"},{"id":"c14e06913e03694af4bcaca18","seq":3,"status":"closing"},{"id":"ccda871f68c948c124df62897","seq":3,"status":"closing"},{"id":"c2e8545461a15d2ca798849d0","seq":3,"status":"closing"},{"id":"c3e0b41860f4d99b444898476","seq":3,"status":"closing"},{"id":"c46ae03b0fc56152ec3ac77ad","seq":3,"status":"closing"},{"id":"c59da2e6f3904471ee7d4976d","seq":3,"status":"closing"},{"id":"c80ce0f0db7d8fc88b6fda123","seq":3,"status":"closing"},{"id":"c98ac0407718711af42272d04","seq":3,"status":"closing"}]}